[
    {
        "id": 1,
        "name": "How to mount a plate",
        "duration": "10:40"
    },
    {
        "id": 2,
        "name": "How to mount a plate",
        "duration": "10:40"
    },
    {
        "id": 3,
        "name": "How to mount a plate",
        "duration": "10:40"
    },
    {
        "id": 4,
        "name": "How to mount a plate",
        "duration": "10:40"
    },
    {
        "id": 5,
        "name": "How to mount a plate",
        "duration": "10:40"
    },
    {
        "id": 6,
        "name": "How to mount a plate",
        "duration": "10:40"
    },
    {
        "id": 7,
        "name": "How to mount a plate",
        "duration": "10:40"
    },
    {
        "id": 8,
        "name": "How to mount a plate",
        "duration": "10:40"
    },
    {
        "id": 9,
        "name": "How to mount a plate",
        "duration": "10:40"
    },
    {
        "id": 10,
        "name": "How to mount a plate",
        "duration": "10:40"
    },
    {
        "id": 11,
        "name": "How to mount a plate",
        "duration": "10:40"
    },
    {
        "id": 12,
        "name": "How to mount a plate",
        "duration": "10:40"
    }
]